tymeventure/world.py
tymeventure/__init__.py
tymeventure/misc.py
tymeventure/commandline.py
tymeventure/unicurses/__init__.py
tymeventure/unicurses/setup.py
tymeventure-0.1.0.dist-info/metadata.json
tymeventure-0.1.0.dist-info/METADATA
tymeventure-0.1.0.dist-info/WHEEL
tymeventure-0.1.0.dist-info/DESCRIPTION.rst
tymeventure-0.1.0.dist-info/RECORD
tymeventure-0.1.0.dist-info/top_level.txt
tymeventure-0.1.0.dist-info/entry_points.txt
