Metadata-Version: 2.0
Name: tymeventure
Version: 0.1.0
Summary: A curses-based adventure game
Home-page: https://github.com/Tymewalk/Tymeventure
Author: Tymewalk
Author-email: none
License: MIT
Keywords: game adventure
Platform: UNKNOWN
Classifier: Development Status :: 3 - Alpha
Classifier: Intended Audience :: Anyone
Classifier: Topic :: Games
Classifier: License :: OSI Approved :: MIT License
Classifier: Programming Language :: Python :: 3
Classifier: Programming Language :: Python :: 3.2
Classifier: Programming Language :: Python :: 3.3
Classifier: Programming Language :: Python :: 3.4
Classifier: Programming Language :: Python :: 3.5
Requires-Dist: pickle
Requires-Dist: random
